networksim_package/NetworkSim.py
networksim_package/__init__.py
NetworkSim_brysonreese-0.0.3.dist-info/LICENSE
NetworkSim_brysonreese-0.0.3.dist-info/METADATA
NetworkSim_brysonreese-0.0.3.dist-info/WHEEL
NetworkSim_brysonreese-0.0.3.dist-info/top_level.txt
NetworkSim_brysonreese-0.0.3.dist-info/RECORD
