Metadata-Version: 2.1
Name: NetworkSim-brysonreese
Version: 0.0.3
Summary: A Network Simulator that randomly generates and calculates minimum paths in a configurable random doubly-weighted graph
Home-page: https://github.com/brysonreese/CS491-FinalProject
Author: Bryson Reese
Author-email: bryson@brysonreese.com
License: UNKNOWN
Project-URL: Bug Tracker, https://github.com/brysonreese/CS491-FinalProject/issues
Platform: UNKNOWN
Classifier: Programming Language :: Python :: 3
Classifier: License :: OSI Approved :: MIT License
Classifier: Operating System :: OS Independent
Requires-Python: >=3.9
License-File: LICENSE
